odoo/addons/l10n_it_vat_settlement_date_rc/README.rst
odoo/addons/l10n_it_vat_settlement_date_rc/__init__.py
odoo/addons/l10n_it_vat_settlement_date_rc/__manifest__.py
odoo/addons/l10n_it_vat_settlement_date_rc/i18n/it.po
odoo/addons/l10n_it_vat_settlement_date_rc/i18n/l10n_it_vat_settlement_date_rc.pot
odoo/addons/l10n_it_vat_settlement_date_rc/models/__init__.py
odoo/addons/l10n_it_vat_settlement_date_rc/models/account_move.py
odoo/addons/l10n_it_vat_settlement_date_rc/readme/CONTRIBUTORS.md
odoo/addons/l10n_it_vat_settlement_date_rc/readme/DESCRIPTION.md
odoo/addons/l10n_it_vat_settlement_date_rc/static/description/icon.png
odoo/addons/l10n_it_vat_settlement_date_rc/static/description/index.html
odoo/addons/l10n_it_vat_settlement_date_rc/tests/__init__.py
odoo/addons/l10n_it_vat_settlement_date_rc/tests/test_account_move.py
odoo/addons/l10n_it_vat_settlement_date_rc/views/account_move_views.xml
odoo_addon_l10n_it_vat_settlement_date_rc-16.0.1.0.0.4.dist-info/METADATA
odoo_addon_l10n_it_vat_settlement_date_rc-16.0.1.0.0.4.dist-info/WHEEL
odoo_addon_l10n_it_vat_settlement_date_rc-16.0.1.0.0.4.dist-info/top_level.txt
odoo_addon_l10n_it_vat_settlement_date_rc-16.0.1.0.0.4.dist-info/RECORD
