Metadata-Version: 2.1
Name: odoo-addon-l10n_it_vat_settlement_date_rc
Version: 16.0.1.0.0.4
Requires-Python: >=3.10
Requires-Dist: odoo-addon-l10n_it_reverse_charge>=16.0dev,<16.1dev
Requires-Dist: odoo-addon-l10n_it_vat_settlement_date>=16.0dev,<16.1dev
Requires-Dist: odoo>=16.0a,<16.1dev
Summary: Use VAT Settlement Date in reverse charge.
Home-page: https://github.com/OCA/l10n-italy/tree/16.0/l10n_it_vat_settlement_date_rc
License: AGPL-3
Author: Marco Colombo, Odoo Community Association (OCA)
Author-email: support@odoo-community.org
Classifier: Programming Language :: Python
Classifier: Framework :: Odoo
Classifier: Framework :: Odoo :: 16.0
Classifier: License :: OSI Approved :: GNU Affero General Public License v3
